{"workflow_definition":{"workflow_uuid":"9891f069-3a3a-4d6c-9054-4badf35dda82","organization_group_uuid":"08b7173e-d3c1-43ab-9376-de81c3731892","name":"Windows Onboarding","description":"","payload":{"comment":"","starts_at":"Personlisation Policies StepId:fe5e7108-bb42-469c-b5e2-b8bee72b9033","steps":{"Personlisation Policies StepId:fe5e7108-bb42-469c-b5e2-b8bee72b9033":{"type":"Parallel","branches":[{"name":"Process 1","comment":"","starts_at":"Install Enterprise Upgrade StepId:3d8f137a-8d5b-4560-90d5-742979d3ec72","steps":{"Install Enterprise Upgrade StepId:3d8f137a-8d5b-4560-90d5-742979d3ec72":{"type":"Action","action":{"action_type":"InstallWindowsProfile","parameters":{"profile_identifier":"f56caf5e-3ba7-4ae5-b9bc-037db387fd2b","profile_name":"Enterprise Upgrade"},"resource_found":true},"is_skip_enabled":false,"timeout_in_minutes":120,"is_retry_enabled":true,"retry_time_interval_in_minutes":15,"retry_attempts":1,"retry_backoff_rate":2.0,"timeout_format":"MINUTE","time_interval_format":"MINUTE","is_delay_enabled":false,"delay_time_interval_in_minutes":0,"name":"Install Enterprise Upgrade StepId:3d8f137a-8d5b-4560-90d5-742979d3ec72","end":true}}},{"name":"Process 2","comment":"","starts_at":"Install WallPaper StepId:c13dbf2e-294d-4758-be8a-420dc30b6570","steps":{"Install WallPaper StepId:c13dbf2e-294d-4758-be8a-420dc30b6570":{"type":"Action","action":{"action_type":"InstallWindowsProfile","parameters":{"profile_identifier":"48412357-25f1-40bc-b689-d70a59b05632","profile_name":"WallPaper"},"resource_found":true},"is_skip_enabled":false,"timeout_in_minutes":120,"is_retry_enabled":true,"retry_time_interval_in_minutes":15,"retry_attempts":1,"retry_backoff_rate":2.0,"timeout_format":"MINUTE","time_interval_format":"MINUTE","is_delay_enabled":false,"delay_time_interval_in_minutes":0,"name":"Install WallPaper StepId:c13dbf2e-294d-4758-be8a-420dc30b6570","end":true}}}],"is_skip_enabled":false,"timeout_in_minutes":0,"is_retry_enabled":false,"retry_time_interval_in_minutes":0,"retry_attempts":0,"retry_backoff_rate":0.0,"is_delay_enabled":false,"delay_time_interval_in_minutes":0,"name":"Personlisation Policies StepId:fe5e7108-bb42-469c-b5e2-b8bee72b9033","next":"Remove Bloatware StepId:c7d9c428-9fc0-448b-ba0c-6b27e171ddb5"},"Remove Bloatware StepId:c7d9c428-9fc0-448b-ba0c-6b27e171ddb5":{"type":"Parallel","branches":[{"name":"Process 1","comment":"","starts_at":"Run Remove Bloatware - Get Help StepId:7336d2ed-87ad-47a5-9439-69430d7e026b","steps":{"Run Remove Bloatware - Get Help StepId:7336d2ed-87ad-47a5-9439-69430d7e026b":{"type":"Action","action":{"parameters":{"script_uuid":"65324b2b-ed8a-4077-aeb8-8cd69b4a3e6f","version_uuid":"00000000-0000-0000-0000-000000000000","script_name":"Remove Bloatware - Get Help"},"action_type":"ExecuteWindowsScript","resource_found":true},"is_skip_enabled":false,"timeout_in_minutes":0,"is_retry_enabled":false,"retry_time_interval_in_minutes":0,"retry_attempts":0,"retry_backoff_rate":0.0,"is_delay_enabled":false,"delay_time_interval_in_minutes":0,"name":"Run Remove Bloatware - Get Help StepId:7336d2ed-87ad-47a5-9439-69430d7e026b","end":true}}},{"name":"Process 2","comment":"","starts_at":"Run Remove Bloatware - Cortana StepId:df005683-0134-4c3a-8411-385b2e969307","steps":{"Run Remove Bloatware - Cortana StepId:df005683-0134-4c3a-8411-385b2e969307":{"type":"Action","action":{"parameters":{"script_uuid":"b9b6784c-5629-4f4a-bcd3-596dc1023504","version_uuid":"00000000-0000-0000-0000-000000000000","script_name":"Remove Bloatware - Cortana"},"action_type":"ExecuteWindowsScript","resource_found":true},"is_skip_enabled":false,"timeout_in_minutes":0,"is_retry_enabled":false,"retry_time_interval_in_minutes":0,"retry_attempts":0,"retry_backoff_rate":0.0,"is_delay_enabled":false,"delay_time_interval_in_minutes":0,"name":"Run Remove Bloatware - Cortana StepId:df005683-0134-4c3a-8411-385b2e969307","end":true}}},{"name":"Process 3","comment":"","starts_at":"Run Bloatware - Feedback Hub StepId:0482f002-67b3-4e29-ad53-98df71be65a5","steps":{"Run Bloatware - Feedback Hub StepId:0482f002-67b3-4e29-ad53-98df71be65a5":{"type":"Action","action":{"parameters":{"script_uuid":"6eb02b07-8bb2-4ab4-a6e6-b1caf19a2167","version_uuid":"00000000-0000-0000-0000-000000000000","script_name":"Bloatware - Feedback Hub"},"action_type":"ExecuteWindowsScript","resource_found":true},"is_skip_enabled":false,"timeout_in_minutes":0,"is_retry_enabled":false,"retry_time_interval_in_minutes":0,"retry_attempts":0,"retry_backoff_rate":0.0,"is_delay_enabled":false,"delay_time_interval_in_minutes":0,"name":"Run Bloatware - Feedback Hub StepId:0482f002-67b3-4e29-ad53-98df71be65a5","end":true}}},{"name":"Process 4","comment":"","starts_at":"Run Bloatware - Remove Maps StepId:25de2e3f-91e7-400b-9615-ac8bf06ac250","steps":{"Run Bloatware - Remove Maps StepId:25de2e3f-91e7-400b-9615-ac8bf06ac250":{"type":"Action","action":{"parameters":{"script_uuid":"68832961-8e3f-488c-bb81-60f510fcb18b","version_uuid":"00000000-0000-0000-0000-000000000000","script_name":"Bloatware - Remove Maps"},"action_type":"ExecuteWindowsScript","resource_found":true},"is_skip_enabled":false,"timeout_in_minutes":0,"is_retry_enabled":false,"retry_time_interval_in_minutes":0,"retry_attempts":0,"retry_backoff_rate":0.0,"is_delay_enabled":false,"delay_time_interval_in_minutes":0,"name":"Run Bloatware - Remove Maps StepId:25de2e3f-91e7-400b-9615-ac8bf06ac250","end":true}}},{"name":"Process 5","comment":"","starts_at":"Run Remove Bloatware - 3D Builder StepId:d3245ea9-4c4c-443c-8f76-4b102512a25c","steps":{"Run Remove Bloatware - 3D Builder StepId:d3245ea9-4c4c-443c-8f76-4b102512a25c":{"type":"Action","action":{"parameters":{"script_uuid":"4a742b19-232e-469b-9c89-635d3325155f","version_uuid":"00000000-0000-0000-0000-000000000000","script_name":"Remove Bloatware - 3D Builder"},"action_type":"ExecuteWindowsScript","resource_found":true},"is_skip_enabled":false,"timeout_in_minutes":0,"is_retry_enabled":false,"retry_time_interval_in_minutes":0,"retry_attempts":0,"retry_backoff_rate":0.0,"is_delay_enabled":false,"delay_time_interval_in_minutes":0,"name":"Run Remove Bloatware - 3D Builder StepId:d3245ea9-4c4c-443c-8f76-4b102512a25c","end":true}}}],"is_skip_enabled":false,"timeout_in_minutes":0,"is_retry_enabled":false,"retry_time_interval_in_minutes":0,"retry_attempts":0,"retry_backoff_rate":0.0,"is_delay_enabled":false,"delay_time_interval_in_minutes":0,"name":"Remove Bloatware StepId:c7d9c428-9fc0-448b-ba0c-6b27e171ddb5","next":"Bitlocker and VPN StepId:80853475-7ffc-4189-8285-5d90b2383279"},"Bitlocker and VPN StepId:80853475-7ffc-4189-8285-5d90b2383279":{"choice":{"if":[{"resource":"Sensor","negation":false,"type":"Resource","rules":[{"type":"Resource","criteria":{"value":"tpm_present","property":"Name","operator":"StringEquals"},"connecting_operator":"And"},{"type":"Resource","criteria":{"value":"True","property":"Value","operator":"BooleanEquals"}}],"connecting_operator":"And"},{"resource":"Sensor","negation":false,"type":"Resource","rules":[{"type":"Resource","criteria":{"value":"tpm_ready","property":"Name","operator":"StringEquals"},"connecting_operator":"And"},{"type":"Resource","criteria":{"value":"True","property":"Value","operator":"BooleanEquals"}}]}],"then":[{"type":"Action","action":{"action_type":"InstallWindowsApplication","parameters":{"application_identifier":"3a5d3984-7b9d-4c8e-b8b8-e4bdb733a08a","product_code":"{9d2a8932-7836-4059-9adc-6d58e6b20431}","version":"latest","package_identifier":"{d9730928-f862-4025-a8aa-58f7e47e2165}","application_name":"Workspace ONE Tunnel","additional_properties":{"application_source_type":"INTERNAL","application_type":"Internal","version":"2.1"}},"policy":{"reinstall_if_removed":false},"resource_found":true},"is_skip_enabled":false,"timeout_in_minutes":120,"is_retry_enabled":true,"retry_time_interval_in_minutes":15,"retry_attempts":1,"retry_backoff_rate":2.0,"timeout_format":"MINUTE","time_interval_format":"MINUTE","is_delay_enabled":false,"delay_time_interval_in_minutes":0,"name":"Install Workspace ONE Tunnel Latest available StepId:5812a179-be0e-4c59-bf37-e6db182aa44f","next":"Install BitLocker Encryption StepId:4c30f96a-61f0-4db2-8b5f-9fe86c433f93"},{"type":"Action","action":{"action_type":"InstallWindowsProfile","parameters":{"profile_identifier":"050f8dc4-67f5-45b4-be6a-5737651da323","profile_name":"BitLocker Encryption"},"resource_found":true},"is_skip_enabled":false,"timeout_in_minutes":120,"is_retry_enabled":true,"retry_time_interval_in_minutes":15,"retry_attempts":1,"retry_backoff_rate":2.0,"timeout_format":"MINUTE","time_interval_format":"MINUTE","is_delay_enabled":false,"delay_time_interval_in_minutes":0,"name":"Install BitLocker Encryption StepId:4c30f96a-61f0-4db2-8b5f-9fe86c433f93","next":"Install VPN Configuration StepId:f53f87c9-4051-4bbc-8a01-2a95e203fa91"},{"type":"Action","action":{"action_type":"InstallWindowsProfile","parameters":{"profile_identifier":"61bdf9e9-39d6-4582-b3da-69d3952fdf58","profile_name":"VPN Configuration"},"resource_found":true},"is_skip_enabled":false,"timeout_in_minutes":120,"is_retry_enabled":true,"retry_time_interval_in_minutes":15,"retry_attempts":1,"retry_backoff_rate":2.0,"timeout_format":"MINUTE","time_interval_format":"MINUTE","is_delay_enabled":false,"delay_time_interval_in_minutes":0,"name":"Install VPN Configuration StepId:f53f87c9-4051-4bbc-8a01-2a95e203fa91","next":"Office Applications StepId:98613634-676c-47fa-8c17-d4f3ca3253ed"}],"policy":{"reevaluate_condition":false,"evaluate_condition_even_without_user_context":false}},"type":"ChoiceV2","name":"Bitlocker and VPN StepId:80853475-7ffc-4189-8285-5d90b2383279","next":"Office Applications StepId:98613634-676c-47fa-8c17-d4f3ca3253ed"},"Office Applications StepId:98613634-676c-47fa-8c17-d4f3ca3253ed":{"type":"Parallel","branches":[{"name":"Process 1","comment":"","starts_at":"Install Microsoft 365 Apps - Business Retail Monthly Enterprise Channel - English US (x64) Latest available StepId:a9dac8a3-ecfc-4454-8b0c-e142439a9203","steps":{"Install Microsoft 365 Apps - Business Retail Monthly Enterprise Channel - English US (x64) Latest available StepId:a9dac8a3-ecfc-4454-8b0c-e142439a9203":{"type":"Action","action":{"action_type":"InstallWindowsApplication","parameters":{"application_identifier":"343c7931-f86e-44fb-b595-a19678a823a4","product_code":"{3197ACA6-4F19-520E-CE2E-36215C959D20}","version":"latest","package_identifier":"{005324B2-5279-7B00-857C-3622C21C3D64}","application_name":"Microsoft 365 Apps - Business Retail Monthly Enterprise Channel - English US (x64)","additional_properties":{"application_source_type":"INTERNAL","application_type":"Internal","version":"16.0.16327.20324"}},"policy":{"reinstall_if_removed":false},"resource_found":true},"is_skip_enabled":false,"timeout_in_minutes":120,"is_retry_enabled":true,"retry_time_interval_in_minutes":15,"retry_attempts":1,"retry_backoff_rate":2.0,"timeout_format":"MINUTE","time_interval_format":"MINUTE","is_delay_enabled":false,"delay_time_interval_in_minutes":0,"name":"Install Microsoft 365 Apps - Business Retail Monthly Enterprise Channel - English US (x64) Latest available StepId:a9dac8a3-ecfc-4454-8b0c-e142439a9203","end":true}}},{"name":"Process 2","comment":"","starts_at":"Install Teams Machine-Wide Installer Latest available StepId:62cb1d26-7590-4233-bbff-1892e18e40cd","steps":{"Install Teams Machine-Wide Installer Latest available StepId:62cb1d26-7590-4233-bbff-1892e18e40cd":{"type":"Action","action":{"action_type":"InstallWindowsApplication","parameters":{"application_identifier":"f046201f-0c58-4ec7-994f-2d1378b8b439","product_code":"{731F6BAA-A986-45A4-8936-7C3AAAAA760B}","version":"latest","package_identifier":"{4009BE0E-5D51-5D91-B94C-D00D7B5FE829}","application_name":"Teams Machine-Wide Installer","additional_properties":{"application_source_type":"INTERNAL","application_type":"Internal","version":"1.4.0.7174"}},"policy":{"reinstall_if_removed":false},"resource_found":true},"is_skip_enabled":false,"timeout_in_minutes":120,"is_retry_enabled":true,"retry_time_interval_in_minutes":15,"retry_attempts":1,"retry_backoff_rate":2.0,"timeout_format":"MINUTE","time_interval_format":"MINUTE","is_delay_enabled":false,"delay_time_interval_in_minutes":0,"name":"Install Teams Machine-Wide Installer Latest available StepId:62cb1d26-7590-4233-bbff-1892e18e40cd","end":true}}}],"is_skip_enabled":false,"timeout_in_minutes":0,"is_retry_enabled":false,"retry_time_interval_in_minutes":0,"retry_attempts":0,"retry_backoff_rate":0.0,"is_delay_enabled":false,"delay_time_interval_in_minutes":0,"name":"Office Applications StepId:98613634-676c-47fa-8c17-d4f3ca3253ed","next":"Productivity Applications StepId:b6c0b77e-7ea4-4cbe-a4c4-5487563e1399"},"Productivity Applications StepId:b6c0b77e-7ea4-4cbe-a4c4-5487563e1399":{"type":"Parallel","branches":[{"name":"Process 1","comment":"","starts_at":"Install Slack Machine-Wide Installer (x86) Latest available StepId:cf48367a-25d2-4abb-a7db-111499e75cd1","steps":{"Install Slack Machine-Wide Installer (x86) Latest available StepId:cf48367a-25d2-4abb-a7db-111499e75cd1":{"type":"Action","action":{"action_type":"InstallWindowsApplication","parameters":{"application_identifier":"6e109c07-4aec-466b-8f03-85b94335b0da","product_code":"{AA26D835-831F-4FBA-B923-A9974FE34DC3}","version":"latest","package_identifier":"{AF13B8F2-70F3-4469-95F5-6F09537227C0}","application_name":"Slack Machine-Wide Installer (x86)","additional_properties":{"application_source_type":"INTERNAL","application_type":"Internal","version":"4.15.0.0"}},"policy":{"reinstall_if_removed":false},"resource_found":true},"is_skip_enabled":false,"timeout_in_minutes":120,"is_retry_enabled":true,"retry_time_interval_in_minutes":15,"retry_attempts":1,"retry_backoff_rate":2.0,"timeout_format":"MINUTE","time_interval_format":"MINUTE","is_delay_enabled":false,"delay_time_interval_in_minutes":0,"name":"Install Slack Machine-Wide Installer (x86) Latest available StepId:cf48367a-25d2-4abb-a7db-111499e75cd1","end":true}}},{"name":"Process 2","comment":"","starts_at":"Install Chrome for Business 64-bit Latest available StepId:6a9570d1-6eeb-48e0-8f83-42f41f6febc9","steps":{"Install Chrome for Business 64-bit Latest available StepId:6a9570d1-6eeb-48e0-8f83-42f41f6febc9":{"type":"Action","action":{"action_type":"InstallWindowsApplication","parameters":{"application_identifier":"d47c9a81-aea3-4cb7-ac1e-dcffa6e51008","product_code":"{BD1AA4A7-50F4-39A0-8715-7C2148D661DD}","version":"latest","package_identifier":"{C1DFDF69-5945-32F2-A35E-EE94C99C7CF4}","application_name":"Chrome for Business 64-bit","additional_properties":{"application_source_type":"INTERNAL","application_type":"Internal","version":"114.0.5735.134"}},"policy":{"reinstall_if_removed":false},"resource_found":true},"is_skip_enabled":false,"timeout_in_minutes":120,"is_retry_enabled":true,"retry_time_interval_in_minutes":15,"retry_attempts":1,"retry_backoff_rate":2.0,"timeout_format":"MINUTE","time_interval_format":"MINUTE","is_delay_enabled":false,"delay_time_interval_in_minutes":0,"name":"Install Chrome for Business 64-bit Latest available StepId:6a9570d1-6eeb-48e0-8f83-42f41f6febc9","end":true}}},{"name":"Process 3","comment":"","starts_at":"Install Cisco Jabber 14 Latest available StepId:81a904e3-83bd-4c96-8c75-5a5b53b877f5","steps":{"Install Cisco Jabber 14 Latest available StepId:81a904e3-83bd-4c96-8c75-5a5b53b877f5":{"type":"Action","action":{"action_type":"InstallWindowsApplication","parameters":{"application_identifier":"3cd22bec-024d-4793-8a3c-0451f76a137f","product_code":"{E6279864-E7A0-460B-A977-C5747139A5EE}","version":"latest","package_identifier":"{6FA51B39-4177-411C-A3A3-5A81C464278B}","application_name":"Cisco Jabber 14","additional_properties":{"application_source_type":"INTERNAL","application_type":"Internal","version":"14.1.4.57561"}},"policy":{"reinstall_if_removed":false},"resource_found":true},"is_skip_enabled":false,"timeout_in_minutes":120,"is_retry_enabled":true,"retry_time_interval_in_minutes":15,"retry_attempts":1,"retry_backoff_rate":2.0,"timeout_format":"MINUTE","time_interval_format":"MINUTE","is_delay_enabled":false,"delay_time_interval_in_minutes":0,"name":"Install Cisco Jabber 14 Latest available StepId:81a904e3-83bd-4c96-8c75-5a5b53b877f5","end":true}}},{"name":"Process 4","comment":"","starts_at":"Install Cisco Webex Meetings Desktop App Latest available StepId:adbc9884-a3c6-429d-9a5f-23fcf37c2f26","steps":{"Install Cisco Webex Meetings Desktop App Latest available StepId:adbc9884-a3c6-429d-9a5f-23fcf37c2f26":{"type":"Action","action":{"action_type":"InstallWindowsApplication","parameters":{"application_identifier":"dc997645-9b4d-4d5d-ab4e-0c36f839aea0","product_code":"{1FC96630-344B-42A0-8C34-9B5D0C00DC89}","version":"latest","package_identifier":"{C599642D-7A3F-4351-ADC5-2BA171B6451E}","application_name":"Cisco Webex Meetings Desktop App","additional_properties":{"application_source_type":"INTERNAL","application_type":"Internal","version":"39.2.1.5"}},"policy":{"reinstall_if_removed":false},"resource_found":true},"is_skip_enabled":false,"timeout_in_minutes":120,"is_retry_enabled":true,"retry_time_interval_in_minutes":15,"retry_attempts":1,"retry_backoff_rate":2.0,"timeout_format":"MINUTE","time_interval_format":"MINUTE","is_delay_enabled":false,"delay_time_interval_in_minutes":0,"name":"Install Cisco Webex Meetings Desktop App Latest available StepId:adbc9884-a3c6-429d-9a5f-23fcf37c2f26","end":true}}}],"is_skip_enabled":false,"timeout_in_minutes":0,"is_retry_enabled":false,"retry_time_interval_in_minutes":0,"retry_attempts":0,"retry_backoff_rate":0.0,"is_delay_enabled":false,"delay_time_interval_in_minutes":0,"name":"Productivity Applications StepId:b6c0b77e-7ea4-4cbe-a4c4-5487563e1399","end":true}},"is_imported":false},"created_on":"2023-06-23T04:42:55.05","created_by":"bb7950d8-e763-4af0-b586-40ef4ccf0d70","modified_on":"2023-06-23T04:52:18.7","modified_by":"bb7950d8-e763-4af0-b586-40ef4ccf0d70","version":"9d67415f-c6aa-40f7-bd8f-cd1845fd6e56","device_type":"WinRT","type":"Default","structured_payload_version":2,"catalog_display":{"display_images":[{"href":"","use_default":true}],"categories":[],"display_name":"","display_description":""},"implicit_workflow":false,"workflow_entities":[{"EntityType":2,"EntityUuid":"f56caf5e-3ba7-4ae5-b9bc-037db387fd2b"},{"EntityType":1,"EntityUuid":"3cd22bec-024d-4793-8a3c-0451f76a137f"},{"EntityType":1,"EntityUuid":"dc997645-9b4d-4d5d-ab4e-0c36f839aea0"},{"EntityType":1,"EntityUuid":"f046201f-0c58-4ec7-994f-2d1378b8b439"},{"EntityType":4,"EntityUuid":"a82ae34d-3b66-4b79-9919-3b3081bad1bb"},{"EntityType":2,"EntityUuid":"050f8dc4-67f5-45b4-be6a-5737651da323"},{"EntityType":3,"EntityUuid":"b9b6784c-5629-4f4a-bcd3-596dc1023504"},{"EntityType":3,"EntityUuid":"68832961-8e3f-488c-bb81-60f510fcb18b"},{"EntityType":3,"EntityUuid":"4a742b19-232e-469b-9c89-635d3325155f"},{"EntityType":2,"EntityUuid":"61bdf9e9-39d6-4582-b3da-69d3952fdf58"},{"EntityType":4,"EntityUuid":"6255cedc-7243-400d-99a2-6bab614ce6fc"},{"EntityType":1,"EntityUuid":"6e109c07-4aec-466b-8f03-85b94335b0da"},{"EntityType":3,"EntityUuid":"65324b2b-ed8a-4077-aeb8-8cd69b4a3e6f"},{"EntityType":1,"EntityUuid":"343c7931-f86e-44fb-b595-a19678a823a4"},{"EntityType":3,"EntityUuid":"6eb02b07-8bb2-4ab4-a6e6-b1caf19a2167"},{"EntityType":2,"EntityUuid":"48412357-25f1-40bc-b689-d70a59b05632"},{"EntityType":1,"EntityUuid":"d47c9a81-aea3-4cb7-ac1e-dcffa6e51008"},{"EntityType":1,"EntityUuid":"3a5d3984-7b9d-4c8e-b8b8-e4bdb733a08a"}],"change_log_description":"","version_id":3,"workflow_attributes":[]},"scripts":[{"script_uuid":"b9b6784c-5629-4f4a-bcd3-596dc1023504","name":"Remove Bloatware - Cortana","description":"","platform":12,"is_idempotent":false,"allowed_in_catalog":true,"script_data":"R2V0LUFwcHhQYWNrYWdlIC1BbGxVc2VycyAtUGFja2FnZVR5cGVGaWx0ZXIgQnVuZGxlIC1OYW1lICIqTWljcm9zb2Z0LjU0OTk4MUMzRjVGMTAqIiB8IFJlbW92ZS1BcHB4UGFja2FnZSAtQWxsVXNlcnMgLUVycm9yQWN0aW9uIFNpbGVudGx5Q29udGludWU=","timeout":30,"script_type":1,"execution_context":2,"platform_architecture":2,"script_variables":[],"user_interaction":false},{"script_uuid":"68832961-8e3f-488c-bb81-60f510fcb18b","name":"Bloatware - Remove Maps","description":"\n","platform":12,"is_idempotent":false,"allowed_in_catalog":true,"script_data":"R2V0LUFwcHhQYWNrYWdlIC1BbGxVc2VycyAtUGFja2FnZVR5cGVGaWx0ZXIgQnVuZGxlIC1OYW1lICIqTWljcm9zb2Z0LldpbmRvd3NNYXBzKiIgfCBSZW1vdmUtQXBweFBhY2thZ2UgLUFsbFVzZXJzIC1FcnJvckFjdGlvbiBTaWxlbnRseUNvbnRpbnVlCg==","timeout":30,"script_type":1,"execution_context":2,"platform_architecture":16,"script_variables":[],"user_interaction":false},{"script_uuid":"4a742b19-232e-469b-9c89-635d3325155f","name":"Remove Bloatware - 3D Builder","description":"","platform":12,"is_idempotent":false,"allowed_in_catalog":false,"script_data":"R2V0LUFwcHhQYWNrYWdlIC1BbGxVc2VycyAtUGFja2FnZVR5cGVGaWx0ZXIgQnVuZGxlIC1OYW1lICIqTWljcm9zb2Z0Lk1pY3Jvc29mdDNEVmlld2VyKiIgfCBSZW1vdmUtQXBweFBhY2thZ2UgLUFsbFVzZXJzIC1FcnJvckFjdGlvbiBTaWxlbnRseUNvbnRpbnVlCg==","timeout":30,"script_type":1,"execution_context":2,"platform_architecture":16,"script_variables":[],"user_interaction":false},{"script_uuid":"65324b2b-ed8a-4077-aeb8-8cd69b4a3e6f","name":"Remove Bloatware - Get Help","description":"","platform":12,"is_idempotent":false,"allowed_in_catalog":false,"script_data":"R2V0LUFwcHhQYWNrYWdlIC1BbGxVc2VycyAtUGFja2FnZVR5cGVGaWx0ZXIgQnVuZGxlIC1OYW1lICIqTWljcm9zb2Z0LkdldEhlbHAqIiB8IFJlbW92ZS1BcHB4UGFja2FnZSAtQWxsVXNlcnMgLUVycm9yQWN0aW9uIFNpbGVudGx5Q29udGludWU=","timeout":30,"script_type":1,"execution_context":2,"platform_architecture":16,"script_variables":[],"user_interaction":false},{"script_uuid":"6eb02b07-8bb2-4ab4-a6e6-b1caf19a2167","name":"Bloatware - Feedback Hub","description":"","platform":12,"is_idempotent":false,"allowed_in_catalog":true,"script_data":"R2V0LUFwcHhQYWNrYWdlIC1BbGxVc2VycyAtUGFja2FnZVR5cGVGaWx0ZXIgQnVuZGxlIC1OYW1lICIqTWljcm9zb2Z0LldpbmRvd3NGZWVkYmFja0h1YioiIHwgUmVtb3ZlLUFwcHhQYWNrYWdlIC1BbGxVc2VycyAtRXJyb3JBY3Rpb24gU2lsZW50bHlDb250aW51ZQo=","timeout":30,"script_type":1,"execution_context":2,"platform_architecture":16,"script_variables":[],"user_interaction":false}],"sensors":[{"sensor_uuid":"a82ae34d-3b66-4b79-9919-3b3081bad1bb","name":"tpm_ready","description":" Returns True/False whether TPM is Ready to be used","platform":12,"query_type":1,"query_response_type":3,"execution_context":"System","execution_architecture":4,"script_data":"IyBSZXR1cm5zIFRydWUvRmFsc2Ugd2hldGhlciBUUE0gaXMgUmVhZHkgdG8gYmUgdXNlZA0KIyBSZXR1cm4gVHlwZTogQm9vbGVhbg0KIyBFeGVjdXRpb24gQ29udGV4dDogU3lzdGVtDQokdHBtPWdldC10cG0NCndyaXRlLW91dHB1dCAkdHBtLlRwbVJlYWR5","script_environment_variables":[]},{"sensor_uuid":"6255cedc-7243-400d-99a2-6bab614ce6fc","name":"tpm_present","description":" Returns True/False whether there is a TPM on the current computer","platform":12,"query_type":1,"query_response_type":3,"execution_context":"System","execution_architecture":4,"script_data":"IyBSZXR1cm5zIFRydWUvRmFsc2Ugd2hldGhlciB0aGVyZSBpcyBhIFRQTSBvbiB0aGUgY3VycmVudCBjb21wdXRlcg0KIyBSZXR1cm4gVHlwZTogQm9vbGVhbg0KIyBFeGVjdXRpb24gQ29udGV4dDogU3lzdGVtDQokdHBtPWdldC10cG0NCndyaXRlLW91dHB1dCAkdHBtLlRwbVByZXNlbnQ=","script_environment_variables":[]}]}